{
    "05445de7-bd55-4e28-83c1-5799fb2c165c" : {
        "module" : "user",
        "command" : "current",
        "method": [
            "GET",
            "OPTIONS"
        ]
    },
    "325c705e-a545-4f79-87db-51ea729c70cf" : {
        "module" : "user",
        "submodule" : "refresh",
        "command" : "token",
        "method" : [
            "GET",
            "OPTIONS"
        ]
    },
    "0c0670ec-2b6d-410b-83d1-f51f5de67fd5" : {
        "module" : "user",
        "command" : "login",
        "method": [
            "POST",
            "OPTIONS"
        ]
    },
    "cea7754e-d924-4e50-8b53-7786f8185d6d" : {
        "module" : "user",
        "command" : "logout",
        "method": [
            "GET",
            "OPTIONS"
        ]
    },
    "2b2364b5-4eca-46f4-a1e7-29df1adae7da" : {
        "module" : "user",
        "submodule" : "login",
        "command" : "blocked",
        "method": [
            "GET",
            "POST",
            "OPTIONS"
        ]
    },
    "0bd02850-e7f1-475e-8723-001e3db88699" : {
        "module" : "user",
        "submodule" : "password",
        "command" : "forgot",
        "method": [
            "GET",
            "POST",
            "OPTIONS"
        ]
    },
    "d09462b0-8a67-43a9-a360-2ea750450f3f" : {
        "module" : "user",
        "submodule" : "password",
        "command" : "forgot",
        "subcommand" : "success",
        "method": [
            "GET",
            "POST",
            "OPTIONS"
        ]
    },
    "0c3e7b89-9100-46c4-abdd-7eb76732166e" : {
        "module" : "user",
        "method": [
            "GET",
            "POST",
            "OPTIONS"
        ]
    },
    "7bc142d4-0578-4309-9714-d079332363ee" : {
        "module" : "user",
        "path" : "/User/{{$uuid}}/",
        "method": [
            "GET",
            "PUT",
            "DELETE",
            "OPTIONS"
        ]
    },
    "69a55262-d324-4990-b0f1-ba2767a72aad" : {
        "module" : "user",
        "path" : "/User/{{$uuid}}/{{$attribute}}",
        "method": [
            "GET",
            "DELETE",
            "OPTIONS"
        ]
    },
    "d0e593d8-b601-4a30-b2cb-ccf0da31f8af" : {
        "module" : "user",
        "command" : "list",
        "method" : [
            "GET",
            "OPTIONS"
        ]
    },
    "5a2392cc-be8c-4b52-acbb-f80c331a72fc" : {
        "module" : "export",
        "method": [
            "GET",
            "POST",
            "OPTIONS"
        ]
    },
    "cd223710-bb97-48ac-85f6-120571065d54" : {
        "module" : "import",
        "method": [
            "GET",
            "POST",
            "OPTIONS"
        ]
    },
    "92a63a25-71de-4d37-88cf-8bd98ab23b8d" : {
        "module" : "fileSystem",
        "command" : "read",
        "method" : [
            "GET",
            "OPTIONS"
        ]
    },
    "d349c424-e66a-4ee2-98fc-8f2ce9bd1980" : {
        "module" : "fileSystem",
        "command" : "write",
        "method" : [
            "POST",
            "OPTIONS"
        ]
    },
    "c938d367-f725-439d-ac88-009414737809" : {
        "module" : "fileSystem",
        "command" : "move",
        "method" : [
            "GET",
            "POST",
            "OPTIONS"
        ]
    },
    "7d850636-7468-44b3-ae02-e316276ef5ea" : {
        "module" : "fileSystem",
        "command" : "upload",
        "method" : [
            "POST",
            "OPTIONS"
        ]
    },
    "d6d63948-3e71-47cd-a037-5027f8f2a4b8" : {
        "module" : "fileSystem",
        "command" : "delete",
        "method" : [
            "DELETE",
            "OPTIONS"
        ]
    },
    "e169c37e-49a0-44d5-9c43-ea9b408643e9" : {
        "module" : "fileSystem",
        "submodule" : "list",
        "command" : "directory",
        "method" : [
            "GET",
            "POST",
            "OPTIONS"
        ]
    },
    "9403e839-4ce0-4be1-a249-ab8e8e5f74b1" : {
        "module" : "fileSystem",
        "submodule" : "list",
        "command" : "file",
        "method" : [
            "GET",
            "POST",
            "OPTIONS"
        ]
    },
    "76f96508-4235-46d0-af6a-2a10a02732e1" : {
        "module" : "fileSystem",
        "submodule" : "list",
        "command" : "tree",
        "method" : [
            "GET",
            "POST",
            "OPTIONS"
        ]
    },
    "54c2f1cf-0d67-4d30-b066-2783ea625264" : {
        "module" : "home",
        "command" : "body",
        "method" : [
            "GET",
            "POST",
            "OPTIONS"
        ]
    },
    "2bae618a-bf67-47a3-a40e-9e0cb444a83f" : {
        "module" : "settings",
        "command" : "body",
        "method" : [
            "GET",
            "POST",
            "OPTIONS"
        ]
    },
    "0fbb1e05-350b-465e-91a1-288ccb55d0a9" : {
        "module" : "settings",
        "submodule" : "controllers",
        "command" : "settings",
        "path": "Settings/Controllers/Settings/{{$node.domain}}",
        "method" : [
            "GET",
            "POST",
            "OPTIONS"
        ]
    },
    "838d8a75-823e-48ed-b29f-da8163fe59a9" : {
        "module" : "settings",
        "submodule" : "controllers",
        "command" : "add",
        "method" : [
            "POST",
            "OPTIONS"
        ]
    },
    "7832c65f-1610-4818-b54b-56e57ae0093b" : {
        "module" : "settings",
        "submodule" : "controllers",
        "command" : "command",
        "path": "Settings/Controllers/{{$node.name}}/{{$node.domain}}",
        "method": [
            "GET",
            "PUT",
            "DELETE",
            "OPTIONS"
        ]
    },
    "427e9a39-ab46-4015-bb7f-3e37faa42ad0" : {
        "module" : "settings",
        "submodule" : "domains",
        "command" : "settings",
        "method" : [
            "GET",
            "POST",
            "OPTIONS"
        ]
    },
    "ad807b3e-c7b4-4c87-8c52-bce212777e89" : {
        "module" : "settings",
        "submodule" : "domains",
        "command" : "add",
        "method" : [
            "POST",
            "OPTIONS"
        ]
    },
    "66a76088-cfe5-42ea-9016-fd8c1536144a" : {
        "module" : "settings",
        "submodule" : "domains",
        "command" : "default",
        "path": "Settings/Domains/Default/{{$uuid}}",
        "method": [
            "POST",
            "OPTIONS"
        ]
    },
    "1fa6325a-4a13-4966-97fd-10678dd330ef" : {
        "module" : "settings",
        "submodule" : "domains",
        "command" : "command",
        "path": "Settings/Domains/{{$node.uuid}}",
        "method": [
            "GET",
            "PUT",
            "DELETE",
            "OPTIONS"
        ]
    },
    "32c6a6ea-7d05-4241-bdb7-59368025b7d7" : {
        "module" : "settings",
        "submodule" : "export",
        "command" : "settings",
        "method" : [
            "GET",
            "POST",
            "OPTIONS"
        ]
    },
    "62659b9a-3300-4f3b-a752-869c9d1c5acd" : {
        "module" : "settings",
        "submodule" : "log",
        "command" : "access",
        "method" : [
            "GET",
            "OPTIONS"
        ]
    },
    "f5ddb40b-0559-4106-9d0e-1cf5cad52604" : {
        "module" : "settings",
        "submodule" : "log",
        "command" : "error",
        "method" : [
            "GET",
            "OPTIONS"
        ]
    },
    "20309eba-c677-417e-8557-67f4fa6ddb80" : {
        "module" : "settings",
        "submodule" : "theme",
        "command" : "settings",
        "method" : [
            "GET",
            "POST",
            "OPTIONS"
        ]
    },
    "2ffeb005-f077-4ebf-9983-17636d609d92" : {
        "module" : "settings",
        "submodule" : "theme",
        "command" : "add",
        "method" : [
            "POST",
            "OPTIONS"
        ]
    },
    "322849b4-6380-4d14-a565-dd328e92a3b7" : {
        "module" : "settings",
        "submodule" : "theme",
        "command" : "command",
        "path": "Settings/Theme/{{$node.uuid}}",
        "method": [
            "GET",
            "PUT",
            "DELETE",
            "OPTIONS"
        ]
    },
    "12fd6498-d50e-4de3-ae54-541be1b50a58" : {
        "module" : "settings",
        "submodule" : "routes",
        "command" : "settings",
        "path": "Settings/Routes/Settings/{{$node.domain}}",
        "method" : [
            "GET",
            "POST",
            "OPTIONS"
        ]
    },
    "45c0539d-91c4-4932-8896-a234e182880c" : {
        "module" : "settings",
        "submodule" : "routes",
        "command" : "add",
        "method" : [
            "POST",
            "OPTIONS"
        ]
    },
    "115c9f0e-00f6-4a35-b423-e3a3869d4934" : {
        "module" : "settings",
        "submodule" : "routes",
        "command" : "one-up",
        "path": "Settings/Routes/1/Up/{{$node.uuid}}/{{$node.domain}}",
        "method": [
            "POST",
            "OPTIONS"
        ]
    },
    "895a9d2d-3f7a-4efa-a3ef-f76583bf0601" : {
        "module" : "settings",
        "submodule" : "routes",
        "command" : "one-down",
        "path": "Settings/Routes/1/Down/{{$node.uuid}}/{{$node.domain}}",
        "method": [
            "POST",
            "OPTIONS"
        ]
    },
    "5ff2bd20-9046-4966-9800-cf71424ec868" : {
        "module" : "settings",
        "submodule" : "routes",
        "command" : "command",
        "path": "Settings/Routes/{{$node.uuid}}/{{$node.domain}}",
        "method": [
            "GET",
            "PUT",
            "DELETE",
            "OPTIONS"
        ]
    },
    "5642e4a6-313e-40eb-9837-6af246c79a62" : {
        "module" : "settings",
        "submodule" : "email",
        "command" : "settings",
        "method" : [
            "GET",
            "POST",
            "OPTIONS"
        ]
    },
    "ee6003e2-f224-43dd-bf15-bf91308dd7cc" : {
        "module" : "settings",
        "submodule" : "email",
        "command" : "add",
        "method" : [
            "POST",
            "OPTIONS"
        ]
    },
    "1e2fc7a7-69d6-40a9-9369-6ce335a3582d" : {
        "module" : "settings",
        "submodule" : "email",
        "command" : "account",
        "subcommand" : "default",
        "path": "Settings/Email/Account/Default/{{$uuid}}",
        "method": [
            "GET",
            "OPTIONS"
        ]
    },
    "e5737e14-09c7-4a6d-b9bc-41234207a480" : {
        "module" : "settings",
        "submodule" : "email",
        "command" : "command",
        "path": "Settings/Email/{{$node.uuid}}",
        "method": [
            "GET",
            "PUT",
            "DELETE",
            "OPTIONS"
        ]
    },
    "68afe695-6df8-49ef-a17f-0e3e989f6e11" : {
        "module" : "admin",
        "path": "admin",
        "method": [
            "CLI"
        ]
    },
    "55b1f34a-05c5-4140-951d-d293fa187b33" : {
        "module" : "system",
        "path": "system",
        "method": [
            "CLI"
        ]
    },
    "a3d71f30-9f11-4bec-bb9a-12cc5d48bf29" : {
        "module" : "user",
        "path": "user",
        "method": [
            "CLI"
        ]
    },
    "fc3ba8ba-f02d-4bdb-93de-6a444a63565a" : {
        "module" : "config",
        "command" : "version",
        "method" : [
            "GET",
            "POST",
            "OPTIONS"
        ]
    },
    "e1ea2486-a2a3-4f27-83b0-de6705aba0aa" : {
        "module" : "source",
        "submodule" : "to",
        "command" : "li",
        "method": [
            "POST",
            "OPTIONS"
        ]
    },
    "fdbfeed4-8ad5-4fd0-94c7-224b00b9a1b8" : {
        "module" : "system",
        "command" : "information",
        "method" : [
            "GET",
            "OPTIONS"
        ]
    },
    "3b23f264-0d77-4f3b-b26a-728fa2075dcc": {
        "module" : "system",
        "submodule" : "update",
        "command" : "cms",
        "method": [
            "GET",
            "OPTIONS"
        ]
    }
}